ppds/__init__.py
ppds/__main__.py
ppds/config.py
ppds/hostfilepatch.py
ppds/instance.py
ppds/repository.py
ppds-0.0.1.dev3.dist-info/DESCRIPTION.rst
ppds-0.0.1.dev3.dist-info/METADATA
ppds-0.0.1.dev3.dist-info/RECORD
ppds-0.0.1.dev3.dist-info/WHEEL
ppds-0.0.1.dev3.dist-info/entry_points.txt
ppds-0.0.1.dev3.dist-info/metadata.json
ppds-0.0.1.dev3.dist-info/top_level.txt
