Metadata-Version: 2.0
Name: ppds
Version: 0.0.1.dev3
Summary: Private Peer Domain Syndication
Home-page: https://github.com/theAeon/Private-Peer-Domain-Syndication
Author: Andrew Donshik
Author-email: andrewdonshik@gmail.com
License: GPL-3.0
Download-URL: https://github.com/theAeon/Private-Peer-Domain-Syndication/tarball/0.0.1.dev1
Keywords: networking
Platform: UNKNOWN
Classifier: Development Status :: 2 - Pre-Alpha
Classifier: Intended Audience :: Developers
Classifier: License :: OSI Approved :: GNU General Public License v3 (GPLv3)
Classifier: Programming Language :: Python :: 3 :: Only
Classifier: Operating System :: POSIX
Classifier: Topic :: Internet :: Name Service (DNS)
Requires-Dist: requests
